gawx/__init__.py
gawx/apis.py
gawx/config.py
gawx/pipeline.py
gawx_python_sdk-0.0.1.dist-info/METADATA
gawx_python_sdk-0.0.1.dist-info/WHEEL
gawx_python_sdk-0.0.1.dist-info/top_level.txt
gawx_python_sdk-0.0.1.dist-info/RECORD
