Metadata-Version: 2.4
Name: gawx-python-sdk
Version: 0.0.1
Summary: Gawx Python SDK
Home-page: https://github.com/gawx-ai/gawx-python-sdk
Author: Gawx
Author-email: support@gawx.ai
Requires-Dist: requests
Requires-Dist: pandas
Requires-Dist: python-dotenv
Dynamic: author
Dynamic: author-email
Dynamic: description
Dynamic: description-content-type
Dynamic: home-page
Dynamic: requires-dist
Dynamic: summary
